dull/__init__.py
dull/_src.py
dull-1.0.0.dist-info/WHEEL
dull-1.0.0.dist-info/METADATA
dull-1.0.0.dist-info/RECORD
