Metadata-Version: 2.1
Name: dull
Version: 1.0.0
Summary: Simple Python decorator to dump cProfile stats
Home-page: https://github.com/samharju/dull
License: MIT
Author: Sami Harju
Author-email: sami.harju@gmail.com
Requires-Python: >=3.8,<4.0
Classifier: License :: OSI Approved :: MIT License
Classifier: Programming Language :: Python :: 3
Classifier: Programming Language :: Python :: 3.10
Classifier: Programming Language :: Python :: 3.8
Classifier: Programming Language :: Python :: 3.9
